Workbook

Sheet Dashboard
B1: DASHBOARD - FERIA DEL AUTOMOVIL 2024
B2: Analisis integral del mercado automotor | Massironi
B4: INDICADORES CLAVE (KPIs)
B5: Total Autos | D5: Precio Promedio | F5: Km Promedio | H5: Ventas Realizadas
B6: =COUNTA(datos!A:A)-1 -> 12 | D6: =AVERAGE(datos!N:N)/1000000 -> 23.9 | F6: =AVERAGE(datos!M:M) -> 27166.667 | H6: =COUNTIF(datos!Q2:Q13,">0") -> 5
B36: FILTROS DISPONIBLES EN LA HOJA 'DATOS'
B37: Para filtrar los datos, ve a la hoja 'datos' y usa las flechas de filtro de la tabla:
B38: - Columna B (marca): Toyota, Ford, Chevrolet, Volkswagen, Peugeot, Renault
B39: - Columna G (provincia): Buenos Aires, Cordoba, Santa Fe, Mendoza, Neuquen, Salta
B40: - Columna I (estado): Nuevo, Usado, Seminuevo
B41: Tip: La tabla TblAutos tiene autofiltros incorporados. Haz clic en las flechas del encabezado para segmentar.

Sheet datos
A1: id_auto | B1: marca | C1: modelo | D1: tipo_combustible | E1: transmision | F1: carroceria | G1: provincia | H1: localidad | I1: estado | J1: origen | K1: fecha_publicacion | L1: anio_fabricacion | M1: kilometraje | N1: precio_ars | O1: puertas | P1: financiacion | Q1: id_venta | R1: fecha_venta | S1: precio_venta | T1: anio_venta | U1: precio_con_financiacion
A2: 1 | B2: Toyota | C2: Corolla | D2: Nafta | E2: Automática | F2: Sedán | G2: Buenos Aires | H2: La Plata | I2: Usado | J2: Nacional | K2: 45306 | L2: 2020 | M2: 45000 | N2: 18500000 | O2: 4 | P2: 1 | Q2: 1 | R2: 45332 | S2: 18500000 | T2: 2024 | U2: =IF(P2=1,N2*1.1,N2) -> 20350000
A3: 2 | B3: Toyota | C3: Hilux | D3: Diésel | E3: Manual | F3: Pickup | G3: Córdoba | H3: Córdoba Capital | I3: Nuevo | J3: Nacional | K3: 45342 | L3: 2024 | M3: 0 | N3: 42000000 | O3: 4 | P3: 0 | U3: =IF(P3=1,N3*1.1,N3) -> 42000000
A4: 3 | B4: Ford | C4: Fiesta | D4: Nafta | E4: Manual | F4: Hatchback | G4: Santa Fe | H4: Rosario | I4: Usado | J4: Nacional | K4: 45356 | L4: 2019 | M4: 68000 | N4: 11800000 | O4: 5 | P4: 1 | Q4: 2 | R4: 45394 | S4: 12000000 | T4: 2024 | U4: =IF(P4=1,N4*1.1,N4) -> 12980000
A5: 4 | B5: Ford | C5: Ranger | D5: Diésel | E5: Automática | F5: Pickup | G5: Mendoza | H5: Godoy Cruz | I5: Seminuevo | J5: Importado | K5: 45392 | L5: 2022 | M5: 22000 | N5: 35000000 | O5: 4 | P5: 0 | U5: =IF(P5=1,N5*1.1,N5) -> 35000000
A6: 5 | B6: Chevrolet | C6: Cruze | D6: Nafta | E6: Automática | F6: Sedán | G6: Buenos Aires | H6: La Plata | I6: Usado | J6: Nacional | K6: 45430 | L6: 2021 | M6: 35000 | N6: 22000000 | O6: 4 | P6: 1 | Q6: 3 | R6: 45448 | S6: 22500000 | T6: 2024 | U6: =IF(P6=1,N6*1.1,N6) -> 24200000
A7: 6 | B7: Chevrolet | C7: Onix | D7: Nafta | E7: Manual | F7: Hatchback | G7: Neuquén | H7: Neuquén | I7: Nuevo | J7: Nacional | K7: 45444 | L7: 2024 | M7: 0 | N7: 16500000 | O7: 5 | P7: 0 | U7: =IF(P7=1,N7*1.1,N7) -> 16500000
A8: 7 | B8: Volkswagen | C8: Gol | D8: Nafta | E8: Manual | F8: Hatchback | G8: Salta | H8: Salta | I8: Usado | J8: Nacional | K8: 45485 | L8: 2018 | M8: 89000 | N8: 12500000 | O8: 5 | P8: 1 | Q8: 4 | R8: 45505 | S8: 12800000 | T8: 2024 | U8: =IF(P8=1,N8*1.1,N8) -> 13750000
A9: 8 | B9: Volkswagen | C9: Amarok | D9: Diésel | E9: Automática | F9: Pickup | G9: Córdoba | H9: Córdoba Capital | I9: Seminuevo | J9: Importado | K9: 45507 | L9: 2023 | M9: 15000 | N9: 38000000 | O9: 4 | P9: 0 | U9: =IF(P9=1,N9*1.1,N9) -> 38000000
A10: 9 | B10: Peugeot | C10: 208 | D10: Nafta | E10: Manual | F10: Hatchback | G10: Santa Fe | H10: Rosario | I10: Nuevo | J10: Nacional | K10: 45550 | L10: 2024 | M10: 0 | N10: 19800000 | O10: 5 | P10: 1 | Q10: 5 | R10: 45567 | S10: 20000000 | T10: 2024 | U10: =IF(P10=1,N10*1.1,N10) -> 21780000
A11: 10 | B11: Peugeot | C11: 3008 | D11: Nafta | E11: Automática | F11: SUV | G11: Mendoza | H11: Godoy Cruz | I11: Nuevo | J11: Importado | K11: 45585 | L11: 2024 | M11: 0 | N11: 32000000 | O11: 5 | P11: 0 | U11: =IF(P11=1,N11*1.1,N11) -> 32000000
A12: 11 | B12: Renault | C12: Kwid | D12: Nafta | E12: Manual | F12: Hatchback | G12: Buenos Aires | H12: La Plata | I12: Nuevo | J12: Nacional | K12: 45601 | L12: 2024 | M12: 0 | N12: 14200000 | O12: 5 | P12: 1 | U12: =IF(P12=1,N12*1.1,N12) -> 15620000
A13: 12 | B13: Renault | C13: Duster | D13: Diésel | E13: Manual | F13: SUV | G13: Neuquén | H13: Neuquén | I13: Usado | J13: Importado | K13: 45629 | L13: 2020 | M13: 52000 | N13: 24500000 | O13: 5 | P13: 0 | U13: =IF(P13=1,N13*1.1,N13) -> 24500000

Sheet Tablas Dinamicas
A1: TABLA 1: Precio Promedio por Marca | E1: TABLA 4: Ventas por Mes
A2: Marca | B2: Precio Promedio (ARS) | C2: Cantidad Autos | E2: Mes | F2: Ventas | G2: Monto Total (ARS)
A3: Toyota | B3: =AVERAGEIF(datos!B:B,A3,datos!N:N) -> 30250000 | C3: =COUNTIF(datos!B:B,A3) -> 2 | E3: Febrero | F3: =COUNTIFS(datos!R:R,">="&DATE(2024,2,1),datos!R:R,"<"&DATE(2024,3,1)) -> 1 | G3: =SUMIFS(datos!S:S,datos!R:R,">="&DATE(2024,2,1),datos!R:R,"<"&DATE(2024,3,1)) -> 18500000
A4: Ford | B4: =AVERAGEIF(datos!B:B,A4,datos!N:N) -> 23400000 | C4: =COUNTIF(datos!B:B,A4) -> 2 | E4: Abril | F4: =COUNTIFS(datos!R:R,">="&DATE(2024,4,1),datos!R:R,"<"&DATE(2024,5,1)) -> 1 | G4: =SUMIFS(datos!S:S,datos!R:R,">="&DATE(2024,4,1),datos!R:R,"<"&DATE(2024,5,1)) -> 12000000
A5: Chevrolet | B5: =AVERAGEIF(datos!B:B,A5,datos!N:N) -> 19250000 | C5: =COUNTIF(datos!B:B,A5) -> 2 | E5: Junio | F5: =COUNTIFS(datos!R:R,">="&DATE(2024,6,1),datos!R:R,"<"&DATE(2024,7,1)) -> 1 | G5: =SUMIFS(datos!S:S,datos!R:R,">="&DATE(2024,6,1),datos!R:R,"<"&DATE(2024,7,1)) -> 22500000
A6: Volkswagen | B6: =AVERAGEIF(datos!B:B,A6,datos!N:N) -> 25250000 | C6: =COUNTIF(datos!B:B,A6) -> 2 | E6: Agosto | F6: =COUNTIFS(datos!R:R,">="&DATE(2024,8,1),datos!R:R,"<"&DATE(2024,9,1)) -> 1 | G6: =SUMIFS(datos!S:S,datos!R:R,">="&DATE(2024,8,1),datos!R:R,"<"&DATE(2024,9,1)) -> 12800000
A7: Peugeot | B7: =AVERAGEIF(datos!B:B,A7,datos!N:N) -> 25900000 | C7: =COUNTIF(datos!B:B,A7) -> 2 | E7: Octubre | F7: =COUNTIFS(datos!R:R,">="&DATE(2024,10,1),datos!R:R,"<"&DATE(2024,11,1)) -> 1 | G7: =SUMIFS(datos!S:S,datos!R:R,">="&DATE(2024,10,1),datos!R:R,"<"&DATE(2024,11,1)) -> 20000000
A8: Renault | B8: =AVERAGEIF(datos!B:B,A8,datos!N:N) -> 19350000 | C8: =COUNTIF(datos!B:B,A8) -> 2
A10: TABLA 2: Cantidad de Autos por Provincia
A11: Provincia | B11: Cantidad | C11: % del Total
A12: Buenos Aires | B12: =COUNTIF(datos!G:G,A12) -> 3 | C12: =B12/SUM($B$12:$B$17) -> 0.25
A13: Córdoba | B13: =COUNTIF(datos!G:G,A13) -> 2 | C13: =B13/SUM($B$12:$B$17) -> 0.16666667
A14: Santa Fe | B14: =COUNTIF(datos!G:G,A14) -> 2 | C14: =B14/SUM($B$12:$B$17) -> 0.16666667
A15: Mendoza | B15: =COUNTIF(datos!G:G,A15) -> 2 | C15: =B15/SUM($B$12:$B$17) -> 0.16666667
A16: Neuquén | B16: =COUNTIF(datos!G:G,A16) -> 2 | C16: =B16/SUM($B$12:$B$17) -> 0.16666667
A17: Salta | B17: =COUNTIF(datos!G:G,A17) -> 1 | C17: =B17/SUM($B$12:$B$17) -> 0.083333333
A19: TABLA 3: Financiación (Sí vs No)
A20: Financiación | B20: Cantidad | C20: % del Total
A21: Con Financiación | B21: =COUNTIF(datos!P:P,1) -> 6 | C21: =B21/SUM($B$21:$B$22) -> 0.5
A22: Sin Financiación | B22: =COUNTIF(datos!P:P,0) -> 6 | C22: =B22/SUM($B$21:$B$22) -> 0.5

Sheet Informe
B1: INFORME ANALITICO - FERIA DEL AUTOMOVIL 2024
B3: 1. OBJETO DEL ANALISIS
B4: El presente informe analiza los datos de la Feria del Automovil correspondientes al periodo enero-diciembre 2024. Se evaluan 12 vehiculos publicados de 6 marcas distintas (Toyota, Ford, Chevrolet, Volkswagen, Peugeot y Renault), distribuidos en 6 provincias argentinas. El objetivo es identificar tendencias de mercado, patrones de precios y comportamiento de la demanda.
B6: 2. DATOS ANALIZADOS
B7: La base de datos relacional consta de 12 tablas normalizadas bajo un esquema dimensional (star schema), con una tabla de hechos principal (fact_auto) y multiples dimensiones. Los datos incluyen: 12 publicaciones de vehiculos, 5 ventas concretadas, 4 tipos de combustible, 3 estados de vehiculo y 4 planes de financiacion.
B9: 3. HALLAZGOS PRINCIPALES
B10: 3.1 Precios por marca:
B11: - Toyota lidera el precio promedio con $30.250.000 (impulsado por la Hilux a $42M), seguido por Peugeot ($25.900.000) y Volkswagen ($25.250.000). Las marcas mas accesibles son Chevrolet ($19.250.000) y Renault ($19.350.000).
B13: 3.2 Distribucion geografica:
B14: - Buenos Aires concentra el 25% de las publicaciones (3 de 12 autos). Las demas provincias muestran una distribucion equilibrada con 1-2 vehiculos cada una. Esto refleja la concentracion poblacional del area metropolitana.
B16: 3.3 Financiacion:
B17: - Existe un equilibrio exacto 50/50 entre vehiculos con y sin financiacion (6 cada uno). Los vehiculos nuevos y de alta gama tienden a no ofrecer financiacion, mientras que los usados y de rango medio si la ofrecen. El recargo por financiacion es del 10%.
... B24: - La tasa de conversion (ventas/publicaciones) es del 41.7%, lo que indica una buena efectividad comercial.
B25: =- La diversificacion geografica es positiva, aunque Buenos Aires mantiene La mayor concentracion. -> #NAME?
B26: {=- La oferta de financiacion equilibrada permite captar tanto compradores de contado como financiados.} -> #NAME?
B28: 5. RECOMENDACIONES
B29: {=- Ampliar La oferta de financiacion en vehiculos premium para aumentar La conversion.} -> #NAME?
B30: {=- Incrementar publicaciones en provincias con menor oferta (Salta, Neuquen) para captar demanda insatisfecha.} -> #NAME?
B31: {=- Monitorear el comportamiento estacional de ventas para optimizar campanas de marketing.} -> #NAME?
B32: =- Considerar La incorporacion de vehiculos electricos e hibridos, actualmente subrepresentados en La oferta. -> #NAME?
B34: Elaborado por: Sistema de Analisis - Feria del Automovil Massironi
B35: Fuente: Base de datos MySQL 8+ | Periodo: Enero - Diciembre 2024

Sheet Metricas Bonus
B1: METRICAS Y FORMULAS ADICIONALES
B3: METRICAS DE MERCADO | C3: VALOR | D3: FORMULA UTILIZADA
B4: Precio Maximo | C4: =MAX(datos!N:N) -> 42000000 | D4: =MAX(datos!N:N)
B5: Precio Minimo | C5: =MIN(datos!N:N) -> 11800000 | D5: =MIN(datos!N:N)
B6: Mediana del Precio | C6: =MEDIAN(datos!N2:N13) -> 20900000 | D6: =MEDIAN(datos!N2:N13)
B7: Desvio Estandar del Precio | C7: =STDEV(datos!N2:N13) -> 10402797 | D7: =STDEV(datos!N2:N13)
B8: Rango de Precios (Max - Min) | C8: =MAX(datos!N:N)-MIN(datos!N:N) -> 30200000 | D8: =MAX(datos!N:N)-MIN(datos!N:N)
B10: METRICAS DE RENDIMIENTO | C10: VALOR | D10: FORMULA UTILIZADA
B11: Tasa de Conversion (ventas/autos) | C11: =COUNTIF(datos!Q2:Q13,">0")/COUNTA(datos!A2:A13) -> 0.41666667 | D11: =COUNTIF(ventas)/COUNTA(autos)
B12: Ticket Promedio de Venta | C12: =AVERAGEIF(datos!S2:S13,">0") -> 17160000 | D12: =AVERAGEIF(datos!S2:S13,">0")
B13: Monto Total Vendido | C13: =SUMIF(datos!S2:S13,">0") -> 85800000 | D13: =SUMIF(datos!S2:S13,">0")
B14: % Autos Nuevos | C14: =COUNTIF(datos!I:I,"Nuevo")/COUNTA(datos!I2:I13) -> 0.41666667 | D14: =COUNTIF(estado,"Nuevo")/total
B15: Km Promedio (solo usados) | C15: =AVERAGEIF(datos!I2:I13,"Usado",datos!M2:M13) -> 57800 | D15: =AVERAGEIF(estado,"Usado",km)
B17: ANTIGUEDAD DE VEHICULOS | C17: VALOR | D17: FORMULA UTILIZADA
B18: Antiguedad Promedio (anios) | C18: {=AVERAGE(2024-datos!L2:L13)} -> 2.0833333 | D18: =AVERAGE(2024-anio_fabricacion)
B19: Auto Mas Antiguo (anio) | C19: =MIN(datos!L2:L13) -> 2018 | D19: =MIN(datos!L2:L13)
B20: Auto Mas Reciente (anio) | C20: =MAX(datos!L2:L13) -> 2024 | D20: =MAX(datos!L2:L13)
B22: ANALISIS POR COMBUSTIBLE | C22: CANTIDAD | D22: PRECIO PROMEDIO
B23: Nafta | C23: =COUNTIF(datos!D:D,"Nafta") -> 8 | D23: =AVERAGEIF(datos!D:D,"Nafta",datos!N:N) -> 18412500
B24: Diesel | C24: =COUNTIF(datos!D:D,"Diésel") -> 4 | D24: =AVERAGEIF(datos!D:D,"Diésel",datos!N:N) -> 34875000
B25: Hibrido | C25: =COUNTIF(datos!D:D,"Híbrido") -> 0
B26: Electrico | C26: =COUNTIF(datos!D:D,"Eléctrico") -> 0
